pianko/FeatureTransformer.py
pianko/__init__.py
pianko/build_pipe.py
pianko/corr_filter.py
pianko/fine_tune.py
pianko/first_tune.py
pianko/nan_statistics.py
pianko/plot_learning_curve.py
pianko/plotting.py
pianko/transformers.py
pianko-0.0.11.dist-info/METADATA
pianko-0.0.11.dist-info/WHEEL
pianko-0.0.11.dist-info/top_level.txt
pianko-0.0.11.dist-info/RECORD
