Metadata-Version: 2.1
Name: pianko
Version: 0.0.11
Summary: Package for df transformations using pandas
Home-page: UNKNOWN
Author: Pavel Ianko
Author-email: <pavel.evgenievich.ianko@gmail.com>
License: UNKNOWN
Keywords: python,pandas,numpy
Platform: UNKNOWN
Classifier: Development Status :: 1 - Planning
Classifier: Programming Language :: Python :: 3
Classifier: Operating System :: Unix
Classifier: Operating System :: MacOS :: MacOS X
Classifier: Operating System :: Microsoft :: Windows
Requires-Dist: numpy
Requires-Dist: pandas
Requires-Dist: sklearn
Requires-Dist: matplotlib
